aiotankerkoenig/__init__.py
aiotankerkoenig/aiotankerkoenig.py
aiotankerkoenig/const.py
aiotankerkoenig/exceptions.py
aiotankerkoenig/models.py
aiotankerkoenig/py.typed
aiotankerkoenig-0.4.2.dist-info/LICENSE
aiotankerkoenig-0.4.2.dist-info/METADATA
aiotankerkoenig-0.4.2.dist-info/WHEEL
aiotankerkoenig-0.4.2.dist-info/RECORD
